Workbook
Name StartRevenue: Inputs!$B$2
Name Growth: Inputs!$B$3
Name CostRatio: Inputs!$B$4
Name OpexGrowth: Inputs!$B$5
Name StartOpex: Inputs!$B$6
Name TaxRate: Inputs!$B$8

Sheet Inputs
A1: Assumption | B1: Value
A2: Revenue 2025 (EUR k) | B2: 1200
A3: Revenue growth | B3: 0.08
A4: Cost of sales ratio | B4: 0.42
A5: Opex growth | B5: 0.03
A6: Opex 2025 (EUR k) | B6: 310
A7: Tax rate | B7: 0.25
A8: Tax rate from 2027 | B8: 0.28

Sheet Model
A1: EUR k | B1: 2025 | C1: =B1+1 | D1: =C1+1 | E1: =D1+1 | F1: =E1+1 | G1: =F1+1
A2: Revenue | B2: =StartRevenue | C2: =B2*(1+Growth) | D2: =C2*(1+Growth) | E2: =D2*(1+Growth) | F2: 1714 | G2: =F2*(1+Growth)
A3: Cost of sales | B3: =B2*CostRatio | C3: =C2*CostRatio | D3: =D2*CostRatio | E3: =E2*0.42 | F3: =F2*CostRatio | G3: =G2*CostRatio
A4: Gross profit | B4: =B2-B3 | C4: =C2-C3 | D4: =D2-D3 | E4: =E2-E3 | F4: =F2-F3 | G4: =G2-G3
A5: Opex | B5: =StartOpex | C5: =B5*(1+OpexGrowth) | D5: =C5*(1+OpexGrowth) | E5: =D5*(1+OpexGrowth) | F5: =E5*(1+OpexGrowth) | G5: =F5*(1+OpexGrowth)
A6: Marketing | B6: 40 | C6: 45 | D6: 50 | E6: 55 | F6: 60 | G6: 65
A7: EBITDA | B7: =B4-B5-B6 | C7: =C4-C5-C6 | D7: =D4-D5-D6 | E7: =E4-E5-E6 | F7: =F4-F5-F6 | G7: =G4-G5-G6
A8: Tax | B8: =MAX(0,B7*TaxRate) | C8: =MAX(0,C7*TaxRate) | D8: =MAX(0,D7*TaxRate) | E8: =MAX(0,E7*TaxRate) | F8: =MAX(0,F7*TaxRate) | G8: =MAX(0,(G7-Dashboard!B6)*TaxRate)
A9: Net income | B9: =B7-B8 | C9: =C7-C8 | D9: =D7-D8 | E9: =E7-E8 | F9: =F7-F8 | G9: =G7-G8
A11: Gross margin | B11: =IF(B2=0,0,B4/B2) | C11: =IF(C2=0,0,C4/C2) | D11: =IF(D2=0,0,D4/D2) | E11: =IF(E2=0,0,E4/E2) | F11: =IF(F2=0,0,F4/F2) | G11: =IF(G2=0,0,G4/G2)

Sheet Dashboard
A1: Summary (EUR k)
A2: Revenue 2025-2030 | B2: =SUM(Model!B2:G2)
A3: EBITDA 2025-2030 | B3: =SUM(Model!B7:G7)
A4: Net income 2030 | B4: =Model!G9
A5: Average gross margin | B5: =AVERAGE(Model!B11:G11)
A6: Bonus pool (10% of 2030 net income) | B6: =Model!G9*0.1
A7: EUR/USD (from the treasury file) | B7: =[1]Rates!$B$2
